setup.cfg
setup.py
qball/__init__.py
qball/qball.py
qball.egg-info/PKG-INFO
qball.egg-info/SOURCES.txt
qball.egg-info/dependency_links.txt
qball.egg-info/requires.txt
qball.egg-info/top_level.txt