Metadata-Version: 1.0
Name: qball
Version: 1.1.0
Summary: Python integration for qball
Home-page: https://github.com/ferrants/qball-python
Author: Matt Ferrante
Author-email: mferrante3@gmail.com
License: (c) Copyright 2014. All Rights Reserved.
Keywords: locking,resource locking,webservice
Platform: UNKNOWN
